peacockprint/__init__.py
peacockprint/peacockprint.py
peacockprint-0.1.0.dist-info/AUTHORS.rst
peacockprint-0.1.0.dist-info/LICENSE
peacockprint-0.1.0.dist-info/METADATA
peacockprint-0.1.0.dist-info/WHEEL
peacockprint-0.1.0.dist-info/entry_points.txt
peacockprint-0.1.0.dist-info/top_level.txt
peacockprint-0.1.0.dist-info/RECORD
