Metadata-Version: 2.1
Name: peacockprint
Version: 0.1.0
Summary: Pretty print text in varioua replacement template and a color tuple.
Home-page: https://github.com/gvido-berzins/peacockprint
Author: Gvido Bērziņš
Author-email: gvido.berzins@syberu.xyz
License: GNU General Public License v3
Keywords: peacockprint
Platform: UNKNOWN
Classifier: Development Status :: 2 - Pre-Alpha
Classifier: Intended Audience :: Developers
Classifier: License :: OSI Approved :: GNU General Public License v3 (GPLv3)
Classifier: Natural Language :: English
Classifier: Programming Language :: Python :: 3
Classifier: Programming Language :: Python :: 3.6
Classifier: Programming Language :: Python :: 3.7
Classifier: Programming Language :: Python :: 3.8
Requires-Python: >=3.6
License-File: LICENSE
License-File: AUTHORS.rst
